airgoodies/__init__.py
airgoodies/aws/s3/__init__.py
airgoodies/aws/s3/wrapper.py
airgoodies/command/__init__.py
airgoodies/command/command.py
airgoodies/command/parser.py
airgoodies/common/__init__.py
airgoodies/common/exception.py
airgoodies/common/variables.py
airgoodies/mongo/__init__.py
airgoodies/mongo/connection.py
airgoodies/task/__init__.py
airgoodies/task/aws_tasks.py
airgoodies/task/config/__init__.py
airgoodies/task/config/task_configuration.py
airgoodies/task/config/variables.py
airgoodies/task/method/__init__.py
airgoodies/task/method/transform.py
airgoodies/util/__init__.py
airgoodies/util/annotation.py
airgoodies/xcom/__init__.py
airgoodies/xcom/manager.py
airgoodies-0.0.4.dist-info/LICENSE
airgoodies-0.0.4.dist-info/METADATA
airgoodies-0.0.4.dist-info/WHEEL
airgoodies-0.0.4.dist-info/top_level.txt
airgoodies-0.0.4.dist-info/RECORD
