Metadata-Version: 2.1
Name: airgoodies
Version: 0.0.4
Summary: Various goodies for Apache Airflow
Author: Stavros Grigoriou
Author-email: unix121@protonmail.com
License-File: LICENSE
Requires-Dist: pymongo ==4.5.0
Requires-Dist: apache-airflow ==2.7.2
Requires-Dist: apache-airflow-providers-amazon ==8.7.1
Requires-Dist: pandas ==2.1.1
Requires-Dist: pyyaml ==6.0.1
